cpskin.cirkwi-1.0.2-py2.7-nspkg.pth
cpskin/cirkwi/__init__.py
cpskin/cirkwi/configure.zcml
cpskin/cirkwi/interfaces.py
cpskin/cirkwi/setuphandlers.py
cpskin/cirkwi/testing.py
cpskin/cirkwi/browser/__init__.py
cpskin/cirkwi/browser/cirkwiview.pt
cpskin/cirkwi/browser/cirkwiview.py
cpskin/cirkwi/browser/configure.zcml
cpskin/cirkwi/browser/static/.gitkeep
cpskin/cirkwi/locales/cpskin.cirkwi.pot
cpskin/cirkwi/locales/plone.pot
cpskin/cirkwi/locales/update.sh
cpskin/cirkwi/locales/en/LC_MESSAGES/cpskin.cirkwi.po
cpskin/cirkwi/locales/en/LC_MESSAGES/plone.po
cpskin/cirkwi/locales/fr/LC_MESSAGES/cpskin.cirkwi.po
cpskin/cirkwi/locales/fr/LC_MESSAGES/plone.po
cpskin/cirkwi/profiles/default/browserlayer.xml
cpskin/cirkwi/profiles/default/cpskincirkwi_default.txt
cpskin/cirkwi/profiles/default/metadata.xml
cpskin/cirkwi/profiles/default/types.xml
cpskin/cirkwi/profiles/default/types/cirkwi.xml
cpskin/cirkwi/tests/__init__.py
cpskin/cirkwi/tests/test_cirkwi.py
cpskin/cirkwi/tests/test_robot.py
cpskin/cirkwi/tests/test_setup.py
cpskin/cirkwi/tests/robot/test_cirkwi.robot
cpskin/cirkwi/tests/robot/test_example.robot
cpskin.cirkwi-1.0.2.dist-info/DESCRIPTION.rst
cpskin.cirkwi-1.0.2.dist-info/METADATA
cpskin.cirkwi-1.0.2.dist-info/RECORD
cpskin.cirkwi-1.0.2.dist-info/WHEEL
cpskin.cirkwi-1.0.2.dist-info/entry_points.txt
cpskin.cirkwi-1.0.2.dist-info/metadata.json
cpskin.cirkwi-1.0.2.dist-info/namespace_packages.txt
cpskin.cirkwi-1.0.2.dist-info/top_level.txt
