Metadata-Version: 2.0
Name: cpskin.cirkwi
Version: 1.0.2
Summary: New product with a specific view for cirkwi - http://outil.cirkwi.com
Home-page: https://pypi.python.org/pypi/cpskin.cirkwi
Author: boulch
Author-email: christophe.boulanger@imio.be
License: GPL version 2
Keywords: Python Plone
Platform: UNKNOWN
Classifier: Environment :: Web Environment
Classifier: Framework :: Plone
Classifier: Framework :: Plone :: 4.3
Classifier: Programming Language :: Python
Classifier: Programming Language :: Python :: 2.7
Classifier: Operating System :: OS Independent
Classifier: License :: OSI Approved :: GNU General Public License v2 (GPLv2)
Provides-Extra: test
Requires-Dist: plone.api
Requires-Dist: plone.app.dexterity
Requires-Dist: plone
Requires-Dist: setuptools
Provides-Extra: test
Requires-Dist: plone.app.testing; extra == 'test'
Requires-Dist: plone.app.robotframework[debug]; extra == 'test'
